spacevader/.gitignore
spacevader/Pipfile
spacevader/Pipfile.lock
spacevader/__init__.py
spacevader/__main__.py
spacevader/cli.py
spacevader/main.py
spacevader/.vscode/settings.json
spacevader/entities/__init__.py
spacevader/entities/__main__.py
spacevader/entities/alien.py
spacevader/entities/bullet.py
spacevader/entities/constant.py
spacevader/entities/player.py
spacevader/icons/alien.png
spacevader/icons/background-1.jpg
spacevader/icons/background-2.jpg
spacevader/icons/bullet.png
spacevader/icons/player.png
spacevader/icons/restart.png
spacevader/icons/ufo.png
spacevader/sounds/background.wav
spacevader/sounds/explosion.wav
spacevader/sounds/laser.wav
spacevader-0.0.4.dist-info/AUTHORS.rst
spacevader-0.0.4.dist-info/LICENSE
spacevader-0.0.4.dist-info/METADATA
spacevader-0.0.4.dist-info/WHEEL
spacevader-0.0.4.dist-info/entry_points.txt
spacevader-0.0.4.dist-info/top_level.txt
spacevader-0.0.4.dist-info/RECORD
