Metadata-Version: 2.1
Name: spacevader
Version: 0.0.4
Summary: A simple space invader game developed purely in Python
Home-page: https://github.com/pratikms/spacevader
Author: Pratik Shivaraikar
Author-email: pratik.shivaraikar@gmail.com
License: MIT
Project-URL: Documentation, https://spacevader.readthedocs.io/
Project-URL: Changelog, https://spacevader.readthedocs.io/en/latest/changelog.html
Project-URL: Issue Tracker, https://github.com/pratikms/spacevader/issues
Keywords: space,invader,vader,spaceinvader,space-invader,spacevader,space-vader,space vader,space invader
Platform: UNKNOWN
Classifier: Development Status :: 5 - Production/Stable
Classifier: Intended Audience :: Developers
Classifier: License :: OSI Approved :: MIT License
Classifier: Operating System :: Unix
Classifier: Operating System :: POSIX
Classifier: Operating System :: Microsoft :: Windows
Classifier: Programming Language :: Python
Classifier: Programming Language :: Python :: 3
Classifier: Programming Language :: Python :: 3.6
Classifier: Programming Language :: Python :: 3.7
Classifier: Programming Language :: Python :: 3.8
Classifier: Programming Language :: Python :: Implementation :: CPython
Classifier: Programming Language :: Python :: Implementation :: PyPy
Classifier: Topic :: Games/Entertainment
Requires-Python: >=3.6
Requires-Dist: pygame (==1.9.6)
Requires-Dist: psutil (==5.6.7)
